{"chunk_definitions":[{"row":13,"row_count":1,"visible":true,"expansion_state":0,"options":{"engine":"r","label":"setup","include":false,"dev":"png"},"document_id":"95D5D80D","chunk_id":"csetup_chunk","chunk_label":"setup"},{"row":38,"row_count":1,"visible":true,"expansion_state":0,"options":{"engine":"r","label":"cleaning costs","dev":"png"},"document_id":"95D5D80D","chunk_id":"ctcrohik305r1","chunk_label":"cleaning costs"},{"row":63,"row_count":1,"visible":true,"expansion_state":0,"options":{"engine":"r","label":"cleaning 2021 cases","dev":"png"},"document_id":"95D5D80D","chunk_id":"ccx4nz135ln4t","chunk_label":"cleaning 2021 cases"},{"row":77,"row_count":1,"visible":true,"expansion_state":0,"options":{"engine":"r","label":"cleaning 2022 cases","dev":"png"},"document_id":"95D5D80D","chunk_id":"cch0364kgecns","chunk_label":"cleaning 2022 cases"},{"row":97,"row_count":1,"visible":true,"expansion_state":0,"options":{"engine":"r","label":"cleaning population","dev":"png"},"document_id":"95D5D80D","chunk_id":"cmdgpsx665iu7","chunk_label":"cleaning population"},{"row":118,"row_count":1,"visible":true,"expansion_state":0,"options":{"engine":"r","label":"joining cases and population","message":false,"dev":"png"},"document_id":"95D5D80D","chunk_id":"cnjewb5onap1h","chunk_label":"joining cases and population"},{"row":131,"row_count":1,"visible":true,"expansion_state":0,"options":{"engine":"r","label":"joining cases and cost","dev":"png"},"document_id":"95D5D80D","chunk_id":"c0zz9wz7oygy5","chunk_label":"joining cases and cost"},{"row":149,"row_count":1,"visible":true,"expansion_state":0,"options":{"engine":"r","label":"codebook","echo":false,"results":true,"dev":"png"},"document_id":"95D5D80D","chunk_id":"c80epsqlexosr","chunk_label":"codebook"},{"row":164,"row_count":1,"visible":true,"expansion_state":0,"options":{"engine":"r","label":"cost summary","include":false,"dev":"png"},"document_id":"95D5D80D","chunk_id":"c54cpar42n2dz","chunk_label":"cost summary"},{"row":183,"row_count":1,"visible":true,"expansion_state":0,"options":{"engine":"r","label":"cost hist","echo":false,"results":true,"dev":"png"},"document_id":"95D5D80D","chunk_id":"c5l7mwrmts5o4","chunk_label":"cost hist"},{"row":193,"row_count":1,"visible":true,"expansion_state":0,"options":{"engine":"r","label":"cases 2021 summary","include":false,"dev":"png"},"document_id":"95D5D80D","chunk_id":"c8tzrdt7bnqhh","chunk_label":"cases 2021 summary"},{"row":212,"row_count":1,"visible":true,"expansion_state":0,"options":{"engine":"r","label":"cases 2021 histogram","echo":false,"results":true,"dev":"png"},"document_id":"95D5D80D","chunk_id":"caf47o0cmfl7o","chunk_label":"cases 2021 histogram"},{"row":222,"row_count":1,"visible":true,"expansion_state":0,"options":{"engine":"r","label":"cases 2022 summary","include":false,"dev":"png"},"document_id":"95D5D80D","chunk_id":"c3v58rlxxo0jj","chunk_label":"cases 2022 summary"},{"row":241,"row_count":1,"visible":true,"expansion_state":0,"options":{"engine":"r","label":"cases 2022 histogram","echo":false,"results":true,"dev":"png"},"document_id":"95D5D80D","chunk_id":"c0xpr93eqvbz2","chunk_label":"cases 2022 histogram"},{"row":259,"row_count":1,"visible":true,"expansion_state":0,"options":{"engine":"r","label":"map data","dev":"png"},"document_id":"95D5D80D","chunk_id":"ci8pl5pfxjy0p","chunk_label":"map data"},{"row":287,"row_count":1,"visible":true,"expansion_state":0,"options":{"engine":"r","label":"map total cases/costs","echo":false,"results":true,"dev":"png"},"document_id":"95D5D80D","chunk_id":"cmg5b31zdtedw","chunk_label":"map total cases/costs"},{"row":297,"row_count":1,"visible":true,"expansion_state":0,"options":{"engine":"r","label":"creating RANK","dev":"png"},"document_id":"95D5D80D","chunk_id":"cf4ip85atyjf4","chunk_label":"creating RANK"},{"row":325,"row_count":1,"visible":true,"expansion_state":0,"options":{"engine":"r","label":"map RANK","echo":false,"results":true,"dev":"png"},"document_id":"95D5D80D","chunk_id":"cr5mesgx64n9y","chunk_label":"map RANK"}],"doc_write_time":1729827376,"working_dir":null,"default_chunk_options":{"echo":true,"warning":false,"message":false}}